apirunner_html/__init__.py
apirunner_html/api.py
apirunner_html/extras.py
apirunner_html/hooks.py
apirunner_html/report.py
apirunner_html/runner.py
apirunner_html/static/css/default.css
apirunner_html/static/css/legency.css
apirunner_html/static/js/capture.js
apirunner_html/static/js/default.js
apirunner_html/static/js/legency.js
apirunner_html/templates/default.html
apirunner_html/templates/legency.html
apirunner_html-1.1.2.dist-info/entry_points.txt
apirunner_html-1.1.2.dist-info/LICENSE
apirunner_html-1.1.2.dist-info/WHEEL
apirunner_html-1.1.2.dist-info/METADATA
apirunner_html-1.1.2.dist-info/RECORD
